<?xml version="1.0" encoding="UTF-8"?>
<page sect="BRIEFE" num="170" base="3.3.2.3.16.178"><div3 xml:id="JG16227" type="Überschrift3" org="uniform" sample="complete" part="N" TEIform="div3"><head TEIform="head"><milestone ed="foliogruppe" unit="JGoethe 1772, Okt., - 73" TEIform="milestone"/><ref target="RBRADD" targOrder="U" TEIform="ref"><anchor xml:id="BRADD" TEIform="anchor"/>144</ref>. An Johanna <ref target="FAHLMERJOHANNA" targOrder="U" TEIform="ref">Fahlmer</ref>, Frankfurt ?. 3. 1773</head><p xml:id="JG16228" rend="Prosatext" TEIform="p"><milestone ed="foliogruppe" unit="JGoethe 1772, Okt., - 73" TEIform="milestone"/>[Frankfurt, März 1773]</p><p xml:id="JG16229" rend="Prosatext" TEIform="p"><milestone ed="foliogruppe" unit="JGoethe 1772, Okt., - 73" TEIform="milestone"/>Einen Morgen gruss hat Ihnen die liebe Sonne schon geben, der besser ist denn meiner. Doch ist auch der nicht zu verachten. Grüsse Sie also und schicke <ref target="WARTONTHOMAS" targOrder="U" TEIform="ref">Warton</ref> und <ref target="GOLDSMITHOLIVER" targOrder="U" TEIform="ref">Wackefield</ref> [Goldsmith] und Was mehr ist - Wörterbuch. Wo sie Bedeutung und Aussprache nach selbst beliebigem Gefallen forschen und finden können. Und dieses geschieht weil es scheinen will als ob Sie noch einige Tage an mir einen unfleissigen lehrmeister haben würden. Denn ich befinde mich in einem Stand von Perturbation in dem es den Seelen, sagen sie, nicht vorteilhafft ist aus der Welt zu gehn. Demohngeachtet, da sich nichts verdrüssliche[s] noch ängstliches einmischt, binn ich dessen wohl zufrieden. Mögen Sie das auch seyn, und an dem so lieblich vorbey fliessenden Wasser nicht allzu lebhafft empfinden wie schön das wäre, wenn Sie geleitet von Frülingssonn und Lufft dahinab seegelten [nach Pempelfort zu Jacobis] zur Freud und Wonne der Auserwählten, dazu uns Gott allen Gnädiglich verhelfen wolle. Amen.</p></div3></page>