<?xml version="1.0" encoding="UTF-8"?>
<page sect="LYRIKANFANG" num="203" base="3.3.2.3.13.209"><div3 xml:id="JG12658" type="Überschrift3" org="uniform" sample="complete" part="N" TEIform="div3"><head TEIform="head"><milestone ed="foliogruppe" unit="JGoethe 1775/3 ab Juli" TEIform="milestone"/><anchor xml:id="SEHNSUCHT" TEIform="anchor"/>Sehnsucht <ref target="LYRIKANFANG" targOrder="U" TEIform="ref"><figure rend="intern" entity="PFEILOB" TEIform="figure"/></ref></head><p xml:id="JG12659" rend="ErlaeuterungenKleinLyrik" TEIform="p"><milestone ed="foliogruppe" unit="JGoethe 1775/3 ab Juli" TEIform="milestone"/><ref target="KSEHNSUCH" targOrder="U" TEIform="ref"><figure rend="intern" entity="PFEILRE" TEIform="figure"/></ref></p><p xml:id="JG12660" rend="Prosatext" TEIform="p"><milestone ed="foliogruppe" unit="JGoethe 1775/3 ab Juli" TEIform="milestone"/><hi TEIform="hi">Melod. O! Vater der Barmherzigkeit etc.</hi></p><lg xml:id="JG12661" type="Strophe" org="uniform" sample="complete" part="N" TEIform="lg"><milestone ed="foliogruppe" unit="JGoethe 1775/3 ab Juli" TEIform="milestone"/><l n="1" part="N" TEIform="l"><anchor xml:id="DIESWIRDDIELETZTETRAHNNICHTSEYN" TEIform="anchor"/>Dies wird die letzte Trähn' nicht seyn</l><l part="N" TEIform="l"> Die glühend Herz auf quillet,</l><l part="N" TEIform="l"> Das mit unsäglich neuer Pein</l><l part="N" TEIform="l"> Sich schmerzvermehrend stillet.</l></lg><lg xml:id="JG12662" type="Strophe" org="uniform" sample="complete" part="N" TEIform="lg"><milestone ed="foliogruppe" unit="JGoethe 1775/3 ab Juli" TEIform="milestone"/><l n="5" part="N" TEIform="l"> O! Laß doch immer hier und dort</l><l part="N" TEIform="l"> Mich ewig Liebe fülen;</l><l part="N" TEIform="l"> Und mögt' der Schmerz auch also fort</l><l part="N" TEIform="l"> Durch Nerv' und Adern wülen.</l></lg><lg xml:id="JG12663" type="Strophe" org="uniform" sample="complete" part="N" TEIform="lg"><milestone ed="foliogruppe" unit="JGoethe 1775/3 ab Juli" TEIform="milestone"/><l part="N" TEIform="l"> Könnt' ich doch ausgefüllt einmal</l><l n="10" part="N" TEIform="l"> Von dir, o Ew'ger werden -</l><l part="N" TEIform="l"> Ach diese lange, tiefe Quaal</l><l part="N" TEIform="l"> Wie dauert sie auf Erden!</l></lg></div3></page>