<?xml version="1.0" encoding="UTF-8"?>
<page sect="AUSDRUCKSFORMEN" num="12" base="3.3.2.9.10.18"><div3 xml:id="JG27152" type="Überschrift3" org="uniform" sample="complete" part="N" TEIform="div3"><head TEIform="head"><anchor xml:id="WILLAMOVBESCHLUS" TEIform="anchor"/>Johann Gottlieb <ref target="WILLAMOVJOHANNGOTTLIEB" targOrder="U" TEIform="ref">Willamov</ref>: Beschlus [1763]</head><p xml:id="JG27153" rend="ErlaeuterungenKlein" TEIform="p">Aus: Willamov, Dithyramben, Berlin 1763. Vorlage: Epochen der deutschen Lyrik. Hrsg. von Walther Killy. Bd. 5 hrsg. von Jürgen Stenzel. München 1969. S. 309f. - Hymnendichtung als Absage an Hymnendichtung.</p><p xml:id="JG27154" rend="ErlaeuterungenKlein" TEIform="p"><ref target="LYRIK" targOrder="U" TEIform="ref"><figure rend="intern" entity="PFEILOB" TEIform="figure"/></ref></p><lg xml:id="JG27155" type="Strophe" org="uniform" sample="complete" part="N" TEIform="lg"><l part="N" TEIform="l">Fahr hin! Fahre hin, Löwenbezwinger [Dionysos]!</l><l part="N" TEIform="l">Und du trunknes Getymmel um ihn</l><l part="N" TEIform="l">Mit Epheu und Reben bekränzet!</l><l part="N" TEIform="l">Fahr hin! - Ich folge nicht mehr!</l></lg><lg xml:id="JG27156" type="Strophe" org="uniform" sample="complete" part="N" TEIform="lg"><l part="N" TEIform="l">Mit vollem Silbergesicht -</l><l part="N" TEIform="l">Und Myrth und Nelken umkränzen sie -</l><l part="N" TEIform="l">Sie flattern mir zu, die Liebesgötter. </l><l part="N" TEIform="l">Gebt mir, gebt mir, Amors! </l><l part="N" TEIform="l">Fittige der Zephirs! -</l><l part="N" TEIform="l">Windet nicht Blumenfesseln um mich! </l><l part="N" TEIform="l">Ich fliege mit euch! - Sie sprossen schon, </l><l part="N" TEIform="l">Ich fyhl es - sie sprossen die Flygel -</l><l part="N" TEIform="l">Begeistrung raft mich gewaltsam hin -</l><l part="N" TEIform="l">Nicht Begeistrung von dir, Bacchus! - -</l><l part="N" TEIform="l">Cypern! - sei mir gesegnet! -</l><l part="N" TEIform="l">Paphos - Gnidus! - ich seh euch. </l><l part="N" TEIform="l">Labyrinthen von Rosen </l><l part="N" TEIform="l">Entduften Scherze mir zu -</l><l part="N" TEIform="l">Gesänge Zärtlichkeit schaffend </l><l part="N" TEIform="l">Schwellen den pochenden Busen - ungestym.</l></lg><lg xml:id="JG27157" type="Strophe" org="uniform" sample="complete" part="N" TEIform="lg"><l part="N" TEIform="l">Fahr hin! Fahre hin, Löwenbezwinger! </l><l part="N" TEIform="l">Und du trunknes Getymmel um ihn </l><l part="N" TEIform="l">Mit Epheu und Reben bekränzet! </l><l part="N" TEIform="l">Fahr hin! - ich folge nicht mehr!</l></lg><lg xml:id="JG27158" type="Strophe" org="uniform" sample="complete" part="N" TEIform="lg"><l part="N" TEIform="l">Sie selber, die Göttin -</l><l part="N" TEIform="l">Sehet, da kommt sie! -</l><l part="N" TEIform="l">Ich bebe neues Gefyhl -</l><l part="N" TEIform="l">Im Purpurwagen als Königin </l><l part="N" TEIform="l">Umweht von Balsam kommt Cythere. </l><l part="N" TEIform="l">Wald und Hygel hypfen </l><l part="N" TEIform="l">Trunken von Entzyckung -</l><l part="N" TEIform="l">Ehrfurcht fesselt die Nereiden -</l><l part="N" TEIform="l">Die Styrme säuseln in Harmonien! - -</l><l part="N" TEIform="l">Umtanzet von Nymphen und Amorn </l><l part="N" TEIform="l">Und nakten Grazien, siegt ihr Blick </l><l part="N" TEIform="l">Fernher. - Lächelt sie mir? - Göttin!</l><l part="N" TEIform="l">Holde Göttin! - ich zittre </l><l part="N" TEIform="l">Ganz Empfindung - Wo bin ich? -</l><l part="N" TEIform="l">Wie? bist du es? - -  Sie ists! </l><l part="N" TEIform="l">Das ist ihr Auge voll Glut! </l><l part="N" TEIform="l">Das ist das Lächeln voll Tugend! -</l><l part="N" TEIform="l">Welche Entzyckung, o DAPHNE, täuschte mich?</l></lg><lg xml:id="JG27159" type="Strophe" org="uniform" sample="complete" part="N" TEIform="lg"><l part="N" TEIform="l">Fahr hin! Fahre hin, Löwenbezwinger! </l><l part="N" TEIform="l">Und du trunknes Getymmel um ihn </l><l part="N" TEIform="l">Mit Epheu und Reben bekränzet!</l><l part="N" TEIform="l">Fahr hin! - Ich folge nicht mehr.</l></lg></div3></page>