<?xml version="1.0" encoding="UTF-8"?>
<page sect="BRIEFE" num="298" base="3.3.2.3.16.306"><div3 xml:id="JG83297" type="Überschrift3" org="uniform" sample="complete" part="N" TEIform="div3"><head TEIform="head"><ref target="RBRBFC" targOrder="U" TEIform="ref"><anchor xml:id="BRBFC" TEIform="anchor"/>263</ref>. An Sophie v. <ref target="LAROCHESOPHIEVON" targOrder="U" TEIform="ref">La Roche</ref>, Frankfurt ca. 20. 8. 1774</head><p xml:id="JG17016" rend="Prosatext" TEIform="p"><milestone ed="foliogruppe" unit="JGoethe 1774/3 Aug-Dez" TEIform="milestone"/>[Frankfurt, etwa 20. August 1774]</p><p xml:id="JG17017" rend="Prosatext" TEIform="p"><milestone ed="foliogruppe" unit="JGoethe 1774/3 Aug-Dez" TEIform="milestone"/>Hier Mama das versprochene [?], ist's so recht? Mit der fahrenden schick ich mehr, vergüldt aufm Schnitt, dabey des lieben Mädgens Briefe ["Rosaliens Briefe"] das ein fürtreffl. Mädgen ist, dabey Zeitungen von Herrn <ref target="DEINETJOHANNCONRAD" targOrder="U" TEIform="ref">Deinet</ref>. Wollen Sie mir dann schreiben, was ich Ihnen soll für den Tee? was Sie ausgelegt haben für mich? so will ichs mit denen 2 Carolin an Dumeix [<ref target="DUMEIZDAMIANFRIEDRICH" targOrder="U" TEIform="ref">Dumeiz</ref>] geben oder wohin Sie wollen. Mit der Alnecht [?] Sill [?] will ich dann warten aber nicht lang. Hat <ref target="HOHENFELDCHRISTOPHWILLIBALDVON" targOrder="U" TEIform="ref">Hohenf.</ref> [Hohenfeld] einen Clavigo [<title type="Goethewerk" TEIform="title">Clavigo</title>]?</p><p xml:id="JG17018" rend="ProsaMitErsteinzug" TEIform="p"><milestone ed="foliogruppe" unit="JGoethe 1774/3 Aug-Dez" TEIform="milestone"/><ref target="GROSCHLAGVONDIEPURGCARLFRIEDRICHWILHELM" targOrder="U" TEIform="ref">Groschl.</ref> [Groschlag] mögt ich gar gerne sehen wenns halbweg mit Manier geschehen kann.</p><p xml:id="JG17019" rend="ProsaMitErsteinzug" TEIform="p"><milestone ed="foliogruppe" unit="JGoethe 1774/3 Aug-Dez" TEIform="milestone"/>D'abord que <ref target="WIELANDCHRISTOPHMARTIN" targOrder="U" TEIform="ref">Wieland</ref> est <hi TEIform="hi">Curieux</hi> de savoir ce que je <hi TEIform="hi">ferois</hi> de lui, si le hasard me l'amenoit - il est perdu - vous m'entendés bien. Sobald ein Werther [<title type="Goethewerk" TEIform="title">Die Leiden des jungen Werthers</title>] kommt, soll er bey Ihnen seyn, hier ist auch wieder das Testament das nicht Cristi ist [Herder, "Älteste Urkunde"].</p></div3></page>