<?xml version="1.0" encoding="UTF-8"?>
<page sect="LYRIKANFANG" num="84" base="3.3.2.3.13.93"><div3 xml:id="JG11775" type="Überschrift3" org="uniform" sample="complete" part="N" TEIform="div3"><head TEIform="head"><milestone ed="foliogruppe" unit="JGoethe 1768-70" TEIform="milestone"/><anchor xml:id="NLDIERELIQUIE" TEIform="anchor"/>Die Reliquie [Neue Lieder] <ref target="LYRIKANFANG" targOrder="U" TEIform="ref"><figure rend="intern" entity="PFEILOB" TEIform="figure"/></ref></head><p xml:id="JG11776" rend="ErlaeuterungenKleinLyrik" TEIform="p"><milestone ed="foliogruppe" unit="JGoethe 1768-70" TEIform="milestone"/><ref target="KRELIQUIE" targOrder="U" TEIform="ref"><figure rend="intern" entity="PFEILRE" TEIform="figure"/></ref></p><p xml:id="JG11777" rend="ErlaeuterungenKleinLyrik" TEIform="p"><milestone ed="foliogruppe" unit="JGoethe 1768-70" TEIform="milestone"/><ref target="LEBENDIGESANDENKEN" targOrder="U" TEIform="ref">Spätere Überlieferung: B (1815)</ref></p><p xml:id="JG11778" rend="ErlaeuterungenKleinLyrik" TEIform="p"><milestone ed="foliogruppe" unit="JGoethe 1768-70" TEIform="milestone"/><ref target="PDIERELIQUIE" targOrder="U" TEIform="ref">Paralleldarstellung</ref></p><lg xml:id="JG11779" type="Strophe" org="uniform" sample="complete" part="N" TEIform="lg"><milestone ed="foliogruppe" unit="JGoethe 1768-70" TEIform="milestone"/><l part="N" TEIform="l"><anchor xml:id="ICHKENNOJUNGLINGDEINEFREUDE" TEIform="anchor"/></l><l n="1" part="N" TEIform="l"><note place="unspecified" anchored="yes" TEIform="note">1815<note place="unspecified" anchored="yes" TEIform="note">Als Goethe fuer den Gedichtband seiner "Werke" (Ausgabe B, Bd. 1, 1815) mit seinen Helfern das Material sichtete, ging er mit feinem Rechen auch die fruehe Periode noch einmal durch und fand noch ein paar Gedichte, u. a. aus den "Neuen Liedern", die ihm - nach entsprechender Redaktion - der Aufnahme wuerdig schienen. Sie werden hier auch in dieser Letztfassung mitgeteilt, damit die Textgeschichte bis an ihr Ende verfolgt werden kann.</note><lb TEIform="lb"/>Der Liebsten Band und Schleife rauben,<lb TEIform="lb"/>
Halb mag sie zürnen, halb erlauben,<lb TEIform="lb"/>
Euch ist es viel, ich will es glauben<lb TEIform="lb"/>
Und gönn' euch solchen Selbstbetrug:<lb TEIform="lb"/>
Ein Schleyer, Halstuch, Strumpfband, Ringe<lb TEIform="lb"/>
Sind wirklich keine kleinen Dinge;<lb TEIform="lb"/>
Allein mir sind sie nicht genug.</note></l><l part="N" TEIform="l">Ich kenn', o Jüngling, deine Freude,</l><l part="N" TEIform="l"> Erwischest du einmal zur Beute</l><l part="N" TEIform="l"> Ein Band, ein Stückgen von dem Kleide,</l><l part="N" TEIform="l"> Das dein geliebtes Mädgen trug.</l><l n="5" part="N" TEIform="l"> Ein Schleyer, Halstuch, Strumpfband, Ringe,</l><l part="N" TEIform="l"> Sind wirklich keine kleinen Dinge,</l><l part="N" TEIform="l"> Allein mir sind sie nicht genug.</l></lg><lg xml:id="JG11780" type="Strophe" org="uniform" sample="complete" part="N" TEIform="lg"><milestone ed="foliogruppe" unit="JGoethe 1768-70" TEIform="milestone"/><l part="N" TEIform="l"><note place="unspecified" anchored="yes" TEIform="note">1815<note place="unspecified" anchored="yes" TEIform="note">Als Goethe fuer den Gedichtband seiner "Werke" (Ausgabe B, Bd. 1, 1815) mit seinen Helfern das Material sichtete, ging er mit feinem Rechen auch die fruehe Periode noch einmal durch und fand noch ein paar Gedichte, u. a. aus den "Neuen Liedern", die ihm - nach entsprechender Redaktion - der Aufnahme wuerdig schienen. Sie werden hier auch in dieser Letztfassung mitgeteilt, damit die Textgeschichte bis an ihr Ende verfolgt werden kann.</note>:<lb TEIform="lb"/>
Lebendig Theil von ihrem Leben,<lb TEIform="lb"/>
Ihn hat, nach leisem Wderstreben,<lb TEIform="lb"/>
Die allerlibste mir gegeben,<lb TEIform="lb"/>
Und jene&gt; Herrlichkeit wird nichts.<lb TEIform="lb"/>
Wie lach ich all der Trödelwaare!<lb TEIform="lb"/>
Sie schenkte mir die schönen Haare,<lb TEIform="lb"/>
Den Schmuck des schönen Angesichts.</note> Mein zweytes Glücke nach dem Leben,</l><l part="N" TEIform="l"> Mein Mädgen hat mir was gegeben,</l><l n="10" part="N" TEIform="l"> Setzt eure Schätze mir darneben,</l><l part="N" TEIform="l"> Und ihre Herrlichkeit wird nichts.</l><l part="N" TEIform="l"> Wie lach ich all der Trödelwaare!</l><l part="N" TEIform="l"> Sie schenkte mir die schönsten Haare,</l><l part="N" TEIform="l"> Den Schmuck des schönen Angesichts.</l></lg><lg xml:id="JG11781" type="Strophe" org="uniform" sample="complete" part="N" TEIform="lg"><l n="15" part="N" TEIform="l"><milestone ed="foliogruppe" unit="JGoethe 1768-70" TEIform="milestone"/><note place="unspecified" anchored="yes" TEIform="note">1815<note place="unspecified" anchored="yes" TEIform="note">Als Goethe fuer den Gedichtband seiner "Werke" (Ausgabe B, Bd. 1, 1815) mit seinen Helfern das Material sichtete, ging er mit feinem Rechen auch die fruehe Periode noch einmal durch und fand noch ein paar Gedichte, u. a. aus den "Neuen Liedern", die ihm - nach entsprechender Redaktion - der Aufnahme wuerdig schienen. Sie werden hier auch in dieser Letztfassung mitgeteilt, damit die Textgeschichte bis an ihr Ende verfolgt werden kann.</note><lb TEIform="lb"/>
Soll ich dich gleich, Geliebte, missen,<lb TEIform="lb"/>
Wirst du mir doch nicht ganz entrißen,<lb TEIform="lb"/>
Zu sehn, zu tändeln und zu küßen<lb TEIform="lb"/>
Bleibt die Reliquie&gt; von dir.<lb TEIform="lb"/>
Gleich ist des Haars und mein Geschicke;<lb TEIform="lb"/>
Sonst buhlten wir mit Einem Glücke<lb TEIform="lb"/>
Um sie, jetzt sind wir fern von ihr.<lb TEIform="lb"/></note></l><lg type="Strophe" org="uniform" sample="complete" part="N" TEIform="lg"><l part="N" TEIform="l">Soll ich dich gleich, Geliebte, mißen,</l><l part="N" TEIform="l"> Wirst du mir doch nicht ganz entrißen,<pb ed="Buchausgabe" n="B2 85" TEIform="pb"/></l><l part="N" TEIform="l"> Zu sehn, zu tändeln und zu küßen,</l><l part="N" TEIform="l"> Bleibt mir der schönste Theil von dir.</l><l part="N" TEIform="l"> Gleich ist des Haars und mein Geschicke,</l><l n="20" part="N" TEIform="l"> Sonst buhlten wir mit einem Glücke</l><l part="N" TEIform="l"> Um sie, jetzt sind wir fern von ihr.</l></lg><lg xml:id="JG11782" type="Strophe" org="uniform" sample="complete" part="N" TEIform="lg"><milestone ed="foliogruppe" unit="JGoethe 1768-70" TEIform="milestone"/><l part="N" TEIform="l"><note place="unspecified" anchored="yes" TEIform="note">1815<note place="unspecified" anchored="yes" TEIform="note">Als Goethe fuer den Gedichtband seiner "Werke" (Ausgabe B, Bd. 1, 1815) mit seinen Helfern das Material sichtete, ging er mit feinem Rechen auch die fruehe Periode noch einmal durch und fand noch ein paar Gedichte, u. a. aus den "Neuen Liedern", die ihm - nach entsprechender Redaktion - der Aufnahme wuerdig schienen. Sie werden hier auch in dieser Letztfassung mitgeteilt, damit die Textgeschichte bis an ihr Ende verfolgt werden kann.</note><lb TEIform="lb"/>
Fest waren wir an sie gehangen;<lb TEIform="lb"/>
Wir streichelten die runden Wangen,<lb TEIform="lb"/>
Uns lockt' und zog ein süß&gt; Verlangen,<lb TEIform="lb"/>
Wir gleiteten zur vollen&gt; Brust.<lb TEIform="lb"/>
O Nebenbuhler, frey von Neide,<lb TEIform="lb"/>
Du süß Geschenk, du schöne Beute,<lb TEIform="lb"/>
Erinnre mich an Glück und Lust.</note>
 Fest waren wir an sie gehangen,</l><l part="N" TEIform="l"> Wir streichelten die runden Wangen,</l><l part="N" TEIform="l"> Und gleiteten oft mit Verlangen</l><l n="25" part="N" TEIform="l"> Von da herab zur rundern Brust.</l><l part="N" TEIform="l"> O Nebenbuhler, frey vom Neide,</l><l part="N" TEIform="l"> Reliquie, du schöne Beute,</l><l part="N" TEIform="l"> Erinnre mich der alten Lust.</l></lg></lg></div3></page>