<?xml version="1.0" encoding="UTF-8"?>
<page sect="LYRIKANFANG" num="100" base="3.3.2.3.13.109"><div3 xml:id="JG11860" type="Überschrift3" org="uniform" sample="complete" part="N" TEIform="div3"><head TEIform="head"><milestone ed="foliogruppe" unit="JGoethe 1770-71" TEIform="milestone"/><anchor xml:id="ESSCHLUGMEINHERZ" TEIform="anchor"/>[Willkommen und Abschied]<lb TEIform="lb"/>[Es schlug mein Herz] <ref target="LYRIKANFANG" targOrder="U" TEIform="ref"><figure rend="intern" entity="PFEILOB" TEIform="figure"/></ref></head><p xml:id="JG11861" rend="ErlaeuterungenKleinLyrik" TEIform="p"><milestone ed="foliogruppe" unit="JGoethe 1770-71" TEIform="milestone"/><ref target="KESSCHLUGMEINHERZ" targOrder="U" TEIform="ref"><figure rend="intern" entity="PFEILRE" TEIform="figure"/></ref></p><p xml:id="JG11862" rend="ErlaeuterungenKleinLyrik" TEIform="p"><milestone ed="foliogruppe" unit="JGoethe 1770-71" TEIform="milestone"/><ref target="WILLKOMMIRIS" targOrder="U" TEIform="ref">Spätere Überlieferung: Iris 1775</ref></p><p xml:id="JG11863" rend="ErlaeuterungenKleinLyrik" TEIform="p"><milestone ed="foliogruppe" unit="JGoethe 1770-71" TEIform="milestone"/><ref target="SWILLKOMM" targOrder="U" TEIform="ref">Spätere Überlieferung: S (1789)</ref></p><p xml:id="JG11864" rend="ErlaeuterungenKleinLyrik" TEIform="p"><milestone ed="foliogruppe" unit="JGoethe 1770-71" TEIform="milestone"/><ref target="PWILLKOMM" targOrder="U" TEIform="ref">Paralleldarstellung</ref></p><lg xml:id="JG11865" type="Strophe" org="uniform" sample="complete" part="N" TEIform="lg"><milestone ed="foliogruppe" unit="JGoethe 1770-71" TEIform="milestone"/><l n="1" part="N" TEIform="l"><anchor xml:id="ESSCHLUGMEINHERTZGESCHWINDZUPFERDE" TEIform="anchor"/>Es Schlug mein Hertz, geschwind zu Pferde</l><l part="N" TEIform="l"> Und fort! wild wie ein Held zur Schlacht<note place="unspecified" anchored="yes" TEIform="note"><hi TEIform="hi">wie ein Held zur Schlacht]</hi> Änderung in H3/S: "Es war gethan fast eh' gedacht", vermutlich, um die humoristische Übertreibung zu tilgen.</note></l><l part="N" TEIform="l"> Der Abend wiegte schon die Erde</l><l part="N" TEIform="l"> Und an den Bergen hieng die Nacht</l><l n="5" part="N" TEIform="l"> Schon stund im Nebelkleid die Eiche</l><l part="N" TEIform="l"> Wie ein gethürmter Riese da,</l><l part="N" TEIform="l"> Wo Finsterniß auß dem Gesträuche</l><l part="N" TEIform="l"> Mit hundert Schwartzen Augen sah</l><l part="N" TEIform="l"> Der Mond von einem Wolkenhügel</l><l n="10" part="N" TEIform="l"> Sah schläfrig aus dem Duft<note place="unspecified" anchored="yes" TEIform="note"><hi TEIform="hi">Duft]</hi> Bei Goethe häufig für 'Dunst', 'Nebel'.</note> hervor</l></lg></div3></page>