<?xml version="1.0" encoding="UTF-8"?>
<page sect="UBERARBEITUNGEN" num="16" base="3.3.2.4.10.23"><div3 xml:id="JG19534" type="Überschrift3" org="uniform" sample="complete" part="N" TEIform="div3"><head TEIform="head"><anchor xml:id="SDIEFREUDEN" TEIform="anchor"/>Die Freuden [S 1789<note place="unspecified" anchored="yes" TEIform="note">Ein "Summa summarum seines Lebens" nannte Goethe die erste Gesamtausgabe seiner Gedichte im achten Band seiner 'Schriften' (Ausgabe S) von 1789. (Italienische Reise, 1. 2. 1788) Vorbereitet wurde diese Ausgabe in zwei Manuskripten; sie wurden von der Weimarer Ausgabe H3 und H4 genannt und bilden mit relativ wenigen Abweichungen die 'Erste Sammlung' und die 'Zweyte Sammlung' der Ausgabe S. Die Gedichte, die vermutlich nicht in der vorweimarischen Zeit entstanden sind, sind mit kleinerem Schriftgrad wiedergegeben.</note>]</head><p xml:id="JG19535" rend="ErlaeuterungenKleinLyrik" TEIform="p"><ref target="OEDIEFREUDEN" targOrder="U" TEIform="ref">Frühere Überlieferung: Oeser-Lieder (1768)</ref></p><p xml:id="JG19536" rend="ErlaeuterungenKleinLyrik" TEIform="p"><ref target="NLDIEFREUDEN" targOrder="U" TEIform="ref">Frühere Überlieferung: Neue Lieder (1769)</ref>. Von dort zum Kommentar. </p><lg xml:id="JG19537" type="Strophe" org="uniform" sample="complete" part="N" TEIform="lg"><l n="1" part="N" TEIform="l"> Es flattert um die Quelle</l><l part="N" TEIform="l"> Die wechselnde Libelle,</l><l part="N" TEIform="l"> Mich freut sie lange schon;</l><l part="N" TEIform="l"> Bald dunkel und bald helle,</l><l n="5" part="N" TEIform="l"> Wie der Cameleon,</l><l part="N" TEIform="l"> Bald roth, bald blau,</l><l part="N" TEIform="l"> Bald blau, bald grün;</l><l part="N" TEIform="l"> O daß ich in der Nähe</l><l part="N" TEIform="l"> Doch ihre Farben sähe!</l></lg><lg xml:id="JG19538" type="Strophe" org="uniform" sample="complete" part="N" TEIform="lg"><l n="1" part="N" TEIform="l">0 Sie schwirrt und schwebet, rastet nie!</l><l part="N" TEIform="l"> Doch still, sie setzt sich an die Weiden.</l><l part="N" TEIform="l"> Da hab' ich sie! da hab' ich sie!</l><l part="N" TEIform="l"> Und nun betracht' ich sie genau,</l><l part="N" TEIform="l"> Und seh' ein traurig - dunkles Blau -</l><l n="15" part="N" TEIform="l"> So geht es dir Zergliedrer deiner Freuden!</l></lg></div3></page>